ultipa/__init__.py
ultipa/configuration/InsertRequestConfig.py
ultipa/configuration/RequestConfig.py
ultipa/configuration/UltipaConfig.py
ultipa/configuration/__init__.py
ultipa/connection/__init__.py
ultipa/connection/clientInfo.py
ultipa/connection/clientType.py
ultipa/connection/commonUql.py
ultipa/connection/connection.py
ultipa/connection/connectionBase.py
ultipa/connection/connectionPool.py
ultipa/connection/connectionPoolMaker.py
ultipa/connection/hostManager.py
ultipa/connection/hostManagerControl.py
ultipa/connection/uqlHelper.py
ultipa/operate/__init__.py
ultipa/operate/algo_extra.py
ultipa/operate/base_extra.py
ultipa/operate/download_extra.py
ultipa/operate/edge_extra.py
ultipa/operate/export_extra.py
ultipa/operate/gql_extra.py
ultipa/operate/graph_extra.py
ultipa/operate/hdc_extra.py
ultipa/operate/index_extra.py
ultipa/operate/lte_ufe_extra.py
ultipa/operate/node_extra.py
ultipa/operate/policy_extra.py
ultipa/operate/property_extra.py
ultipa/operate/schema_extra.py
ultipa/operate/task_extra.py
ultipa/operate/uql_extra.py
ultipa/operate/user_extra.py
ultipa/printer/__init__.py
ultipa/printer/prettyPrint.py
ultipa/printer/treeNode.py
ultipa/proto/__init__.py
ultipa/proto/ultipa_pb2.py
ultipa/proto/ultipa_pb2_grpc.py
ultipa/structs/Algo.py
ultipa/structs/BaseModel.py
ultipa/structs/DBType.py
ultipa/structs/Edge.py
ultipa/structs/EncryptType.py
ultipa/structs/EntityRow.py
ultipa/structs/Graph.py
ultipa/structs/GraphSet.py
ultipa/structs/HDC.py
ultipa/structs/Index.py
ultipa/structs/InsertErrorCode.py
ultipa/structs/InsertType.py
ultipa/structs/Job.py
ultipa/structs/License.py
ultipa/structs/Node.py
ultipa/structs/Path.py
ultipa/structs/PointType.py
ultipa/structs/Policy.py
ultipa/structs/Privilege.py
ultipa/structs/Process.py
ultipa/structs/Projection.py
ultipa/structs/Property.py
ultipa/structs/PropertyPrivilege.py
ultipa/structs/PropertyType.py
ultipa/structs/QLType.py
ultipa/structs/Replica.py
ultipa/structs/ResultType.py
ultipa/structs/Retry.py
ultipa-5.2.1.dist-info/METADATA
ultipa-5.2.1.dist-info/WHEEL
ultipa-5.2.1.dist-info/top_level.txt
ultipa-5.2.1.dist-info/RECORD
