Metadata-Version: 2.4
Name: ultipa
Version: 5.2.1
Summary: Pure Python Ultipa Driver
Home-page: https://www.ultipa.com/document/ultipa-drivers/python-installation
Author: Ultipa
Author-email: support@ultipa.com
License: PSF
Keywords: ultipa sdk,ultipa graph
Requires-Python: >=3.9,<3.13
Requires-Dist: grpcio==1.62.3
Requires-Dist: grpcio-tools==1.62.3
Requires-Dist: protobuf==4.25.3
Requires-Dist: google==3.0.0
Requires-Dist: schedule==1.2.2
Requires-Dist: prettytable==3.9.0
Requires-Dist: treelib==1.7.1
Requires-Dist: tzdata==2024.2
Requires-Dist: tzlocal==5.2
Requires-Dist: pytz==2025.2
Requires-Dist: requests==2.32.3
Requires-Dist: future==1.0.0
Requires-Dist: python-dateutil==2.8.2
Dynamic: author
Dynamic: author-email
Dynamic: description
Dynamic: description-content-type
Dynamic: home-page
Dynamic: keywords
Dynamic: license
Dynamic: requires-dist
Dynamic: requires-python
Dynamic: summary
